webload/__init__.py
webload/__main__.py
webload/cli.py
webload/config/__init__.py
webload/config/settings.py
webload/integration/__init__.py
webload/integration/pdf_processor.py
webload/providers/__init__.py
webload/providers/aftermarket.py
webload/providers/base.py
webload/providers/openai.py
webload/providers/paypal.py
webload/providers/wise.py
webload-0.1.1.dist-info/METADATA
webload-0.1.1.dist-info/WHEEL
webload-0.1.1.dist-info/entry_points.txt
webload-0.1.1.dist-info/RECORD
